cognitrix/__init__.py
cognitrix/agents/__init__.py
cognitrix/agents/assistant.py
cognitrix/agents/base.py
cognitrix/agents/core.py
cognitrix/agents/templates.py
cognitrix/app.py
cognitrix/cli.py
cognitrix/config.py
cognitrix/llms/__init__.py
cognitrix/llms/anthropic_llm.py
cognitrix/llms/base.py
cognitrix/llms/clarifai_llm.py
cognitrix/llms/cohere_llm.py
cognitrix/llms/google_llm.py
cognitrix/llms/groq_llm.py
cognitrix/llms/local_llm.py
cognitrix/llms/mindsdb_llm.py
cognitrix/llms/ollama_llm.py
cognitrix/llms/openai_llm.py
cognitrix/llms/session.py
cognitrix/llms/together_llm.py
cognitrix/tasks/__init__.py
cognitrix/tasks/base.py
cognitrix/tools/__init__.py
cognitrix/tools/base.py
cognitrix/tools/misc.py
cognitrix/tools/python.py
cognitrix/tools/tool.py
cognitrix/transcriber.py
cognitrix/utils/__init__.py
cognitrix-0.2.5.dist-info/LICENSE
cognitrix-0.2.5.dist-info/METADATA
cognitrix-0.2.5.dist-info/WHEEL
cognitrix-0.2.5.dist-info/entry_points.txt
cognitrix-0.2.5.dist-info/RECORD
