Metadata-Version: 2.1
Name: cognitrix
Version: 0.2.5
Summary: Package for creating AI Agents using llms
Home-page: https://github.com/theonlyamos/cognitrix
License: Apache2
Keywords: cognitrix,ai,agents,ai agents,ai-agents,llms,autonomous agents
Author: theonlyamos
Author-email: theonlyamos@gmail.com
Requires-Python: >=3.12,<4.0
Classifier: Development Status :: 3 - Alpha
Classifier: Intended Audience :: Developers
Classifier: License :: OSI Approved :: Apache Software License
Classifier: License :: Other/Proprietary License
Classifier: Operating System :: OS Independent
Classifier: Programming Language :: Python :: 3
Classifier: Programming Language :: Python :: 3.12
Classifier: Programming Language :: Python :: 3.10
Classifier: Programming Language :: Python :: 3.11
Classifier: Programming Language :: Python :: 3.6
Classifier: Programming Language :: Python :: 3.7
Classifier: Programming Language :: Python :: 3.8
Classifier: Programming Language :: Python :: 3.9
Classifier: Topic :: Software Development :: Build Tools
Classifier: Topic :: Software Development :: Libraries :: Python Modules
Requires-Dist: aiofiles (>=23.2.1,<24.0.0)
Requires-Dist: aiohttp (>=3.9.3,<4.0.0)
Requires-Dist: anthropic (>=0.17.0,<0.18.0)
Requires-Dist: beautifulsoup4 (>=4.12.3,<5.0.0)
Requires-Dist: clarifai (>=10.1.0,<11.0.0)
Requires-Dist: cohere (>=5.5.6,<6.0.0)
Requires-Dist: deepgram-sdk (==3.*)
Requires-Dist: flask (>=3.0.3,<4.0.0)
Requires-Dist: google-generativeai (>=0.4.0,<0.5.0)
Requires-Dist: groq (>=0.4.1,<0.5.0)
Requires-Dist: ollama (>=0.2.0,<0.3.0)
Requires-Dist: openai (>=1.12.0,<2.0.0)
Requires-Dist: pillow (>=10.2.0,<11.0.0)
Requires-Dist: pyaudio (>=0.2.14,<0.3.0)
Requires-Dist: pyautogui (>=0.9.54,<0.10.0)
Requires-Dist: pydantic (>=2.6.2,<3.0.0)
Requires-Dist: pydub (>=0.25.1,<0.26.0)
Requires-Dist: python-dotenv (>=1.0.1,<2.0.0)
Requires-Dist: requests (>=2.31.0,<3.0.0)
Requires-Dist: tavily-python (>=0.3.3,<0.4.0)
Requires-Dist: together (>=0.2.11,<0.3.0)
Requires-Dist: uuid (>=1.30,<2.0)
Requires-Dist: uvicorn (>=0.30.1,<0.31.0)
Requires-Dist: xmltodict (>=0.13.0,<0.14.0)
Project-URL: Bug Tracker, https://github.com/theonlyamos/cognitrix/issues
Project-URL: Repository, https://github.com/theonlyamos/cognitrix
